is_seven/__init__.py
is_seven/is_seven.py
is_seven-0.1.0.dist-info/LICENSE
is_seven-0.1.0.dist-info/METADATA
is_seven-0.1.0.dist-info/WHEEL
is_seven-0.1.0.dist-info/top_level.txt
is_seven-0.1.0.dist-info/RECORD
