Metadata-Version: 2.1
Name: is-seven
Version: 0.1.0
Summary: A library to check if a number is seven
Home-page: https://github.com/cwingho/is-seven
Author: Brian Chan
Author-email: chanwingho94@gmail.com
Project-URL: Bug Reports, https://github.com/cwingho/is-seven/issues
Project-URL: Source, https://github.com/cwingho/is-seven
Keywords: seven,number,validation
Classifier: Development Status :: 5 - Production/Stable
Classifier: Intended Audience :: Developers
Classifier: Topic :: Software Development :: Libraries :: Python Modules
Classifier: Programming Language :: Python :: 3
Classifier: Programming Language :: Python :: 3.6
Classifier: Programming Language :: Python :: 3.7
Classifier: Programming Language :: Python :: 3.8
Classifier: Programming Language :: Python :: 3.9
Classifier: Programming Language :: Python :: 3.10
Classifier: Programming Language :: Python :: 3.11
Classifier: License :: OSI Approved :: MIT License
Classifier: Operating System :: OS Independent
Requires-Python: >=3.6
License-File: LICENSE
